scSpatial/__init__.py
scSpatial/analysis.py
scSpatial/app.py
scSpatial/dataset.py
scSpatial/segmentation.py
scSpatial/utility.py
scSpatial/viewer.py
scSpatial/widgets/__init__.py
scSpatial/widgets/analysis.py
scSpatial/widgets/loaddata.py
scSpatial/widgets/main_widget.py
scSpatial/widgets/segmentation.py
scSpatial/widgets/visualization.py
scSpatial-0.1.2.dist-info/LICENSE
scSpatial-0.1.2.dist-info/METADATA
scSpatial-0.1.2.dist-info/WHEEL
scSpatial-0.1.2.dist-info/entry_points.txt
scSpatial-0.1.2.dist-info/top_level.txt
scSpatial-0.1.2.dist-info/RECORD
