Metadata-Version: 2.1
Name: scSpatial
Version: 0.1.2
Summary: Package used to analyse spatial transcriptomics data with build in segmentation and information transfer
Author: Jon E.T. Jakobsson
Author-email: jetjakobsson@gmail.com
Keywords: spatial,transcriptomics,scRNA-seq
Classifier: Development Status :: 3 - Alpha
Classifier: Programming Language :: Python :: 3
Classifier: License :: OSI Approved :: MIT License
Requires-Python: >=3.7
License-File: LICENSE
Requires-Dist: scanpy
Requires-Dist: Napari
Requires-Dist: cellpose
Requires-Dist: scikit-image
Requires-Dist: plotly
Requires-Dist: PyQtWebEngine
